readme.rst
rstdoc/__init__.py
rstdoc/dcx.py
rstdoc/fromdocx.py
rstdoc/listtable.py
rstdoc/reference.docx
rstdoc/reference.odt
rstdoc/reference.tex
rstdoc/reflow.py
rstdoc/reimg.py
rstdoc/retable.py
rstdoc/untable.py
rstdoc/wafw.py
rstdoc-1.8.2.data/data/man/man1/rstdoc.1
rstdoc-1.8.2.dist-info/LICENSE
rstdoc-1.8.2.dist-info/METADATA
rstdoc-1.8.2.dist-info/WHEEL
rstdoc-1.8.2.dist-info/entry_points.txt
rstdoc-1.8.2.dist-info/top_level.txt
rstdoc-1.8.2.dist-info/RECORD
