Metadata-Version: 2.1
Name: rstdoc
Version: 1.8.2
Summary: rstdoc - support documentation in restructedText (rst)
Home-page: https://github.com/rstdoc/rstdoc
Author: Roland Puntaier
Author-email: roland.puntaier@gmail.com
License: MIT
Keywords: Documentation
Classifier: Development Status :: 4 - Beta
Classifier: Environment :: Console
Classifier: License :: OSI Approved :: MIT License
Classifier: Natural Language :: English
Classifier: Operating System :: OS Independent
Classifier: Programming Language :: Python :: 3
Classifier: Intended Audience :: End Users/Desktop
Classifier: Intended Audience :: Information Technology
Classifier: Topic :: Utilities
License-File: LICENSE
Requires-Dist: cffi
Requires-Dist: cairocffi
Requires-Dist: cairosvg
Requires-Dist: pillow
Requires-Dist: pyx
Requires-Dist: pyfca
Requires-Dist: pygal
Requires-Dist: numpy
Requires-Dist: matplotlib
Requires-Dist: sympy
Requires-Dist: pint (>=0.14)
Requires-Dist: drawsvg
Requires-Dist: svgwrite
Requires-Dist: stpl (>=1.13.6)
Requires-Dist: pypandoc
Requires-Dist: docutils
Requires-Dist: sphinx
Requires-Dist: sphinx-bootstrap-theme
Requires-Dist: gitpython
Requires-Dist: pyyaml
Requires-Dist: txdir
Provides-Extra: build
Requires-Dist: waf ; extra == 'build'
Provides-Extra: develop
Requires-Dist: mock ; extra == 'develop'
Requires-Dist: virtualenv ; extra == 'develop'
Requires-Dist: pytest-coverage ; extra == 'develop'
